Metadata-Version: 2.1
Name: boticordpy
Version: 3.0.3
Summary: A Python wrapper for BotiCord API
Home-page: https://github.com/boticord/boticordpy
Author: Marakarka
Author-email: support@kerdoku.top
License: MIT
Project-URL: Documentation, https://py.boticord.top/en/stable
Project-URL: Issue tracker, https://github.com/boticord/boticordpy/issues
Classifier: License :: OSI Approved :: MIT License
Classifier: Programming Language :: Python :: 3
Classifier: Programming Language :: Python :: 3.8
Classifier: Programming Language :: Python :: 3.9
Classifier: Programming Language :: Python :: 3.10
Requires-Python: >= 3.8
License-File: LICENSE.txt
